README.md
setup.py
esrpoise/__init__.py
esrpoise/_version.py
esrpoise/costfunctions.py
esrpoise/main.py
esrpoise/optpoise.py
esrpoise/xepr_link.py
esrpoise.egg-info/PKG-INFO
esrpoise.egg-info/SOURCES.txt
esrpoise.egg-info/dependency_links.txt
esrpoise.egg-info/requires.txt
esrpoise.egg-info/top_level.txt