Metadata-Version: 2.1
Name: esrpoise
Version: 1.0.0
Summary: POISE for ESR
Home-page: https://github.com/foroozandehgroup/esrpoise
Author: Mohammadali Foroozandeh, Jean-Baptiste Verstraete, Jonathan Yong
Author-email: mohammadali.foroozandeh@chem.ox.ac.uk
License: UNKNOWN
Platform: UNKNOWN
Classifier: Programming Language :: Python :: 3.7
Classifier: Programming Language :: Python :: 3.8
Classifier: Programming Language :: Python :: 3.9
Classifier: License :: OSI Approved :: GNU General Public License v3 or later (GPLv3+)
Classifier: Operating System :: OS Independent
Requires-Python: >=3.7
